thunder/__about__.py
thunder/__init__.py
thunder/__main__.py
thunder/cli/__init__.py
pyro_thunder-0.0.0.dev2.dist-info/METADATA
pyro_thunder-0.0.0.dev2.dist-info/WHEEL
pyro_thunder-0.0.0.dev2.dist-info/entry_points.txt
pyro_thunder-0.0.0.dev2.dist-info/licenses/LICENSE
pyro_thunder-0.0.0.dev2.dist-info/RECORD
