Metadata-Version: 2.1
Name: pyro-thunder
Version: 0.0.0.dev2
Summary: Probabilistic modeling framework to define, experiment with, and critique models in service of iterating through Box's loop.
Project-URL: Documentation, https://cameronraysmith.github.io/pyro-thunder/
Project-URL: Issues, https://github.com/cameronraysmith/pyro-thunder/issues
Project-URL: Source, https://github.com/cameronraysmith/pyro-thunder
Author-email: pyro-thunder <cameron.ray.smith@gmail.com>
License-File: LICENSE
Classifier: Programming Language :: Python :: 3 :: Only
Requires-Python: >=3.10
Requires-Dist: click
